{"chunk_definitions":[{"chunk_id":"czaan5d2h5d8y","chunk_label":"unnamed-chunk-1","document_id":"EE22D2FB","expansion_state":0,"options":{"echo":false,"engine":"r","label":"unnamed-chunk-1","message":false,"warning":false},"row":59,"row_count":1,"visible":true},{"chunk_id":"c6686vovyor0c","chunk_label":"roosts","document_id":"EE22D2FB","expansion_state":0,"options":{"echo":false,"engine":"r","label":"roosts","message":false,"results":"asis","warning":false},"row":67,"row_count":1,"visible":true},{"chunk_id":"czkcvdn5rmk21","chunk_label":"unnamed-chunk-2","document_id":"EE22D2FB","expansion_state":0,"options":{"echo":false,"engine":"r","label":"unnamed-chunk-2","message":false,"warning":false},"row":114,"row_count":1,"visible":true},{"chunk_id":"ch7f37v2cpjeu","chunk_label":"aic","document_id":"EE22D2FB","expansion_state":0,"options":{"echo":false,"engine":"r","label":"aic","message":false,"warning":false},"row":127,"row_count":1,"visible":true}],"doc_write_time":1585587919}